Metadata-Version: 2.1
Name: placeholderfile
Version: 1.2
Summary: Generates placeholderfile name
Home-page: https://github.com/theroyakash/placeholderfile
Author: theroyakash
Author-email: royakashappleid@icloud.com
License: Apache License
Download-URL: https://github.com/theroyakash/placeholderfile/tarball/main
Platform: UNKNOWN
